diffdates/main.py
diffdates-1.0.1.dist-info/entry_points.txt
diffdates-1.0.1.dist-info/WHEEL
diffdates-1.0.1.dist-info/METADATA
diffdates-1.0.1.dist-info/RECORD
